Workbook

Sheet Dataset Tax & Tax Base
A1: Tax Collection & Tax Base
A4: Sr.No | B4: Years | C4: Direct Taxes | D4: Sales -imports | E4: Sales - Domestic | F4: Total Sales Tax | G4: FEDERAL | H4: CUSTOMS | I4: TOTAL | J4: %change in Total tax | K4: GDP | L4: GDP-non agr | M4: Agri GDP | N4: LSM | O4: Total imports | P4: Dutiable imports
A5: 1 | B5: 2000-01 | C5: 124585 | D5: 88554 | E5: 65011 | F5: =SUM(D5:E5) -> 153565 | G5: 49080 | H5: 65047 | I5: 392277 | K5: 5655818 | L5: =K5-M5 -> 4290223 | M5: 1365595 | N5: 453039 | O5: 627000 | P5: 386597
A6: 2 | B6: 2001-02 | C6: 142505 | D6: 92779 | E6: 73782 | F6: =SUM(D6:E6) -> 166561 | G6: 47186 | H6: 47818 | I6: 404070 | J6: =((I6-I5)/I5)*100 -> 3.006294 | K6: 6030117 | L6: =K6-M6 -> 4661122 | M6: 1368995 | N6: 475458 | O6: 634630 | P6: 404641
A7: 3 | B7: 2002-03 | C7: 151898 | D7: 105605 | E7: 89534 | F7: =SUM(D7:E7) -> 195139 | G7: 44754 | H7: 68836 | I7: 460627 | J7: =((I7-I6)/I6)*100 -> 13.996832 | K7: 6581623 | L7: =K7-M7 -> 5123666 | M7: 1457957 | N7: 530308 | O7: 714372 | P7: 436316
A8: 4 | B8: 2003-04 | C8: 165079 | D8: 125875 | E8: 93292 | F8: =SUM(D8:E8) -> 219167 | G8: 45552 | H8: 91045 | I8: 520843 | J8: =((I8-I7)/I7)*100 -> 13.072616 | K8: 7611678 | L8: =K8-M8 -> 5936965 | M8: 1674713 | N8: 677586 | O8: 897825 | P8: 629159
A9: 5 | B9: 2004-05 | C9: 183372 | D9: 144845 | E9: 93692 | F9: =SUM(D9:E9) -> 238537 | G9: 53104 | H9: 115374 | I9: 590387 | J9: =((I9-I8)/I8)*100 -> 13.3522 | K9: 8619232 | L9: =K9-M9 -> 6759675 | M9: 1859557 | N9: 871600 | O9: 1223079 | P9: 869815
A10: 6 | B10: 2005-06 | C10: 224988 | D10: 171445 | E10: 123353 | F10: =SUM(D10:E10) -> 294798 | G10: 55272 | H10: 138384 | I10: 713442 | J10: =((I10-I9)/I9)*100 -> 20.843108 | K10: 9689071 | L10: =K10-M10 -> 7710723 | M10: 1978348 | N10: 1059972 | O10: 1711158 | P10: 1052837
A11: 7 | B11: 2006-07 | C11: 333737 | D11: 175909 | E11: 133487 | F11: =SUM(D11:E11) -> 309396 | G11: 71804 | H11: 132299 | I11: 847236 | J11: =((I11-I10)/I10)*100 -> 18.753311 | K11: 11165234 | L11: =K11-M11 -> 8939115 | M11: 2226119 | N11: 1208353 | O11: 1851806 | P11: 1010603
A12: 8 | B12: 2007-08 | C12: 387861 | D12: 196034 | E12: 181396 | F12: =SUM(D12:E12) -> 377430 | G12: 92137 | H12: 150663 | I12: 1008091 | J12: =((I12-I11)/I11)*100 -> 18.985855 | K12: 12647137 | L12: =K12-M12 -> 10073272 | M12: 2573865 | N12: 1465583 | O12: 2512072 | P12: 1283696
A13: 9 | B13: 2008-09 | C13: 443548.3 | D13: 203715 | E13: 248029 | F13: =SUM(D13:E13) -> 451744 | G13: 117455 | H13: 148403 | I13: 1161150.3 | J13: =((I13-I12)/I12)*100 -> 15.183084 | K13: 14705698 | L13: =K13-M13 -> 11501779 | M13: 3203919 | N13: 1576860 | O13: 2723570 | P13: 1337629
A14: 10 | B14: 2009-10 | C14: 525977.1 | D14: 247246 | E14: 269102 | F14: =SUM(D14:E14) -> 516348 | G14: 124784.1 | H14: 160272.7 | I14: 1327381.9 | J14: =((I14-I13)/I13)*100 -> 14.316114 | K14: 16507053 | L14: =K14-M14 -> 12761799 | M14: 3745254 | N14: 1810245 | O14: 2910975 | P14: 1333709
A15: 11 | B15: 2010-11 | C15: 602451 | D15: 308648 | E15: 324709 | F15: =SUM(D15:E15) -> 633357 | G15: 137353 | H15: 184853 | I15: 1558014 | J15: =((I15-I14)/I14)*100 -> 17.374962 | K15: 19731030 | L15: =K15-M15 -> 15031169 | M15: 4699861 | N15: 2206129 | O15: 3455286 | P15: 1521329
A16: 12 | B16: 2011-12 | C16: 738424 | D16: 430399 | E16: 374500 | F16: =SUM(D16:E16) -> 804899 | G16: 122464 | H16: 216906 | I16: 1882693 | J16: =((I16-I15)/I15)*100 -> 20.839286 | K16: 22344639 | L16: =K16-M16 -> 17119078 | M16: 5225561 | N16: 2556200 | O16: 4009093 | P16: 1600186
A17: 13 | B17: 2012-13 | C17: 743409 | D17: 429831 | E17: 412697 | F17: =SUM(D17:E17) -> 842528 | G17: 120964 | H17: 239459 | I17: 1946360 | J17: =((I17-I16)/I16)*100 -> 3.3816985 | K17: 25042169 | L17: =K17-M17 -> 19105273 | M17: 5936896 | N17: 2757695 | O17: 4349880 | P17: 1652823
A18: 14 | B18: 2013-14 | C18: 877255 | D18: 495330 | E18: 501052 | F18: =SUM(D18:E18) -> 996382 | G18: 138084 | H18: 242811 | I18: 2254532 | J18: =((I18-I17)/I17)*100 -> 15.833248 | K18: 27952815 | L18: =K18-M18 -> 21385935 | M18: 6566880 | N18: 3075033 | O18: 4634974 | P18: 1778444
A19: 15 | B19: 2014-15 | C19: 1033720 | D19: 553028 | E19: 534762 | F19: =SUM(D19:E19) -> 1087790 | G19: 162248 | H19: 306220 | I19: =+H19+G19+E19+D19+C19 -> 2589978 | J19: =((I19-I18)/I18)*100 -> 14.878742 | K19: 30425880 | L19: =K19-M19 -> 23347956 | M19: 7077924 | N19: 2990836 | O19: 4719399 | P19: 2703371
A20: 16 | B20: 2015-16 | C20: 1217474 | D20: 678313 | E20: 624058 | F20: =SUM(D20:E20) -> 1302371 | G20: 188055 | H20: 404572 | I20: =+H20+G20+E20+D20+C20 -> 3112472 | J20: =((I20-I19)/I19)*100 -> 20.173685 | K20: 32725049 | L20: =K20-M20 -> 25418092 | M20: 7306957 | N20: 2841709 | O20: 4721978 | P20: 3467318
A21: 17 | B21: 2016-17 | C21: 1344226 | D21: 702565 | E21: 626400 | F21: =SUM(D21:E21) -> 1328965 | G21: 197911 | H21: 496772 | I21: =+H21+G21+E21+D21+C21 -> 3367874 | J21: =((I21-I20)/I20)*100 -> 8.2057606 | K21: 35552819 | L21: =K21-M21 -> 27744281 | M21: 7808538 | N21: 3083146 | O21: 5583637 | P21: 4067138
A22: 18 | B22: 2017-18 | C22: 1536583 | D22: 824219 | E22: 661087 | F22: =SUM(D22:E22) -> 1485306 | G22: 213493 | H22: 608373 | I22: =+H22+G22+E22+D22+C22 -> 3843755 | J22: =((I22-I21)/I21)*100 -> 14.130012 | K22: 39189810 | L22: =K22-M22 -> 30704732 | M22: 8485078 | N22: 3499175 | O22: 6749678 | P22: 4662323
A23: 19 | B23: 2018-19 | C23: 1445508 | D23: 810357 | E23: 648856 | F23: =SUM(D23:E23) -> 1459213 | G23: 238186 | H23: 685575 | I23: =+H23+G23+E23+D23+C23 -> 3828482 | J23: =((I23-I22)/I22)*100 -> -0.39734582 | K23: 43798401 | L23: =K23-M23 -> 34741824 | M23: 9056577 | N23: 4266145 | O23: 7499468 | P23: 5054709
A24: 20 | B24: 2019-20 | C24: 1523064 | D24: 876333 | E24: 720471 | F24: =SUM(D24:E24) -> 1596804 | G24: 250470 | H24: 626378 | I24: =+H24+G24+E24+D24+C24 -> 3996716 | J24: =((I24-I23)/I23)*100 -> 4.3942743 | K24: 47540409 | L24: =K24-M24 -> 37150865 | M24: 10389544 | N24: 4026236 | O24: 7057323 | P24: 4455140
A25: 21 | B25: 2020-21 | C25: 1731253 | D25: 1115912 | E25: 872393 | F25: =SUM(D25:E25) -> 1988305 | G25: 277046 | H25: 748390 | I25: =+H25+G25+E25+D25+C25 -> 4744994 | J25: =((I25-I24)/I24)*100 -> 18.722321 | K25: 55836225 | L25: =K25-M25 -> 43182336 | M25: 12653889 | N25: 4933633 | O25: 8984377 | P25: 4268621
A26: 22 | B26: 2021-22 | C26: 2284916 | D26: 1740692 | E26: 791536 | F26: =SUM(D26:E26) -> 2532228 | G26: 320658 | H26: 1010694 | I26: =+H26+G26+E26+D26+C26 -> 6148496 | J26: =((I26-I25)/I25)*100 -> 29.578583 | K26: 66657868 | L26: =K26-M26 -> 51775256 | M26: 14882612 | N26: 7040683 | O26: 14273394 | P26: 6421248
A27: 23 | B27: 2022-23 | C27: 3270820 | D27: 1593590 | E27: 997844 | F27: =SUM(D27:E27) -> 2591434 | G27: 369885 | H27: 931727 | I27: =+H27+G27+E27+D27+C27 -> 7163866 | J27: =((I27-I26)/I26)*100 -> 16.51412 | K27: 83650830 | L27: =K27-M27 -> 64054198 | M27: 19596632 | N27: 8536018 | O27: 13472988 | P27: 5265423 | Q27: given dutiable imports decreased by 18% in this year according to FBR
A28: 24 | B28: 2023-24 | C28: 4530731 | D28: 1863947 | E28: 1222885 | F28: =SUM(D28:E28) -> 3086832 | G28: 577451 | H28: 1104066 | I28: =+H28+G28+E28+D28+C28 -> 9299080 | J28: =((I28-I27)/I27)*100 -> 29.805331 | K28: 105379298 | L28: =K28-M28 -> 80403649 | M28: 24975649 | N28: 10138638 | O28: 15482120 | P28: 8296831
A29: 25 | B29: 2024-25 | C29: 5791667 | D29: 2281854 | E29: 1619518 | F29: =SUM(D29:E29) -> 3901372 | G29: 766641 | H29: 1284608 | I29: =+H29+G29+E29+D29+C29 -> 11744288 | J29: =((I29-I28)/I28)*100 -> 26.29516 | K29: 113934970 | L29: =K29-M29 -> 87739134 | M29: 26195836 | N29: 10445059 | O29: 16306753 | P29: 8159961
A30: 26 | B30: 2025-26 | C30: 6902000 | D30: =0.61*F30 -> 2899330 | E30: =F30*0.39 -> 1853670 | F30: 4753000 | G30: 888000 | H30: 1588000 | I30: 14131000 | J30: =((I30-I29)/I29)*100 -> 20.322322 | K30: 126195000 | L30: =K30-M30 -> 97170150 | M30: =K30*0.23 -> 29024850 | N30: =(N29*(4.9/100)+N29) -> 10956867 | O30: 18497000 | P30: =0.47*O30 -> 8693590
C33: Data Sources: Federal Board of Revenue (FBR) Forecasting 2024–25; FBR Yearbook 2024–25; Budget Brief 2025–26; Ministry of Finance (MoF) Estimates, Pakistan Bureau of Statistics
C34: Note: Total sales figures were available for 2025-26; therefore, the historical sales tax on import-to-total sales ratio (average of the past five years) was applied to estimate import sales and the same was done for domestic good sales tax
C35: Agriculture GDP for 2025–26 is estimated by applying the last five-year average agriculture share in GDP (23%) to total GDP. Dutiable imports are estimated by applying the last five-year average dutiable share of total imports (47%) to total imports (goods).

Sheet Tax Buoyancy Estimates
A1: Tax Buoyancy Estimates
B5: Years | C5: Tax collection | J5: Tax bases
C6: DT | D6: STM | E6: STD | F6: FED | G6: CD | H6: TOTAL | J6: GDP | K6: GDP-non agr | L6: LSM | M6: Total imports | N6: Dutiable imports
B7: 2000-01 | C7: =LOG('Dataset Tax & Tax Base'!C5) -> 5.0954658 | D7: =LOG('Dataset Tax & Tax Base'!D5) -> 4.9472082 | E7: =LOG('Dataset Tax & Tax Base'!E5) -> 4.8129868 | F7: =LOG('Dataset Tax & Tax Base'!G5) -> 4.6909046 | G7: =LOG('Dataset Tax & Tax Base'!H5) -> 4.8132273 | H7: =LOG('Dataset Tax & Tax Base'!I5) -> 5.5935928 | J7: =LOG('Dataset Tax & Tax Base'!K5) -> 6.7524954 | K7: =LOG('Dataset Tax & Tax Base'!L5) -> 6.6324799 | L7: =LOG('Dataset Tax & Tax Base'!N5) -> 5.6561356 | M7: =LOG('Dataset Tax & Tax Base'!O5) -> 5.7972675 | N7: =LOG('Dataset Tax & Tax Base'!P5) -> 5.5872585
B8: 2001-02 | C8: =LOG('Dataset Tax & Tax Base'!C6) -> 5.1538301 | D8: =LOG('Dataset Tax & Tax Base'!D6) -> 4.9674497 | E8: =LOG('Dataset Tax & Tax Base'!E6) -> 4.8679504 | F8: =LOG('Dataset Tax & Tax Base'!G6) -> 4.6738132 | G8: =LOG('Dataset Tax & Tax Base'!H6) -> 4.6795914 | H8: =LOG('Dataset Tax & Tax Base'!I6) -> 5.6064566 | J8: =LOG('Dataset Tax & Tax Base'!K6) -> 6.7803257 | K8: =LOG('Dataset Tax & Tax Base'!L6) -> 6.6684905 | L8: =LOG('Dataset Tax & Tax Base'!N6) -> 5.6771122 | M8: =LOG('Dataset Tax & Tax Base'!O6) -> 5.8025206 | N8: =LOG('Dataset Tax & Tax Base'!P6) -> 5.6070699
B9: 2002-03 | C9: =LOG('Dataset Tax & Tax Base'!C7) -> 5.1815521 | D9: =LOG('Dataset Tax & Tax Base'!D7) -> 5.0236845 | E9: =LOG('Dataset Tax & Tax Base'!E7) -> 4.951988 | F9: =LOG('Dataset Tax & Tax Base'!G7) -> 4.6508319 | G9: =LOG('Dataset Tax & Tax Base'!H7) -> 4.8378156 | H9: =LOG('Dataset Tax & Tax Base'!I7) -> 5.6633494 | J9: =LOG('Dataset Tax & Tax Base'!K7) -> 6.818333 | K9: =LOG('Dataset Tax & Tax Base'!L7) -> 6.7095808 | L9: =LOG('Dataset Tax & Tax Base'!N7) -> 5.7245282 | M9: =LOG('Dataset Tax & Tax Base'!O7) -> 5.8539244 | N9: =LOG('Dataset Tax & Tax Base'!P7) -> 5.6398011
B10: 2003-04 | C10: =LOG('Dataset Tax & Tax Base'!C8) -> 5.2176918 | D10: =LOG('Dataset Tax & Tax Base'!D8) -> 5.0999395 | E10: =LOG('Dataset Tax & Tax Base'!E8) -> 4.9698444 | F10: =LOG('Dataset Tax & Tax Base'!G8) -> 4.6585074 | G10: =LOG('Dataset Tax & Tax Base'!H8) -> 4.9592561 | H10: =LOG('Dataset Tax & Tax Base'!I8) -> 5.7167068 | J10: =LOG('Dataset Tax & Tax Base'!K8) -> 6.8814804 | K10: =LOG('Dataset Tax & Tax Base'!L8) -> 6.7735645 | L10: =LOG('Dataset Tax & Tax Base'!N8) -> 5.8309644 | M10: =LOG('Dataset Tax & Tax Base'!O8) -> 5.9531917 | N10: =LOG('Dataset Tax & Tax Base'!P8) -> 5.7987604
B11: 2004-05 | C11: =LOG('Dataset Tax & Tax Base'!C9) -> 5.263333 | D11: =LOG('Dataset Tax & Tax Base'!D9) -> 5.1609035 | E11: =LOG('Dataset Tax & Tax Base'!E9) -> 4.9717025 | F11: =LOG('Dataset Tax & Tax Base'!G9) -> 4.7251272 | G11: =LOG('Dataset Tax & Tax Base'!H9) -> 5.0621079 | H11: =LOG('Dataset Tax & Tax Base'!I9) -> 5.7711368 | J11: =LOG('Dataset Tax & Tax Base'!K9) -> 6.9354686 | K11: =LOG('Dataset Tax & Tax Base'!L9) -> 6.8299258 | L11: =LOG('Dataset Tax & Tax Base'!N9) -> 5.9403172 | M11: =LOG('Dataset Tax & Tax Base'!O9) -> 6.0874545 | N11: =LOG('Dataset Tax & Tax Base'!P9) -> 5.9394269
B12: 2005-06 | C12: =LOG('Dataset Tax & Tax Base'!C10) -> 5.3521594 | D12: =LOG('Dataset Tax & Tax Base'!D10) -> 5.2341248 | E12: =LOG('Dataset Tax & Tax Base'!E10) -> 5.0911497 | F12: =LOG('Dataset Tax & Tax Base'!G10) -> 4.7425052 | G12: =LOG('Dataset Tax & Tax Base'!H10) -> 5.1410859 | H12: =LOG('Dataset Tax & Tax Base'!I10) -> 5.8533587 | J12: =LOG('Dataset Tax & Tax Base'!K10) -> 6.9862821 | K12: =LOG('Dataset Tax & Tax Base'!L10) -> 6.8870951 | L12: =LOG('Dataset Tax & Tax Base'!N10) -> 6.0252944 | M12: =LOG('Dataset Tax & Tax Base'!O10) -> 6.2332901 | N12: =LOG('Dataset Tax & Tax Base'!P10) -> 6.0223611
B13: 2006-07 | C13: =LOG('Dataset Tax & Tax Base'!C11) -> 5.5234044 | D13: =LOG('Dataset Tax & Tax Base'!D11) -> 5.2452881 | E13: =LOG('Dataset Tax & Tax Base'!E11) -> 5.125439 | F13: =LOG('Dataset Tax & Tax Base'!G11) -> 4.8561486 | G13: =LOG('Dataset Tax & Tax Base'!H11) -> 5.1215566 | H13: =LOG('Dataset Tax & Tax Base'!I11) -> 5.9280044 | J13: =LOG('Dataset Tax & Tax Base'!K11) -> 7.0478678 | K13: =LOG('Dataset Tax & Tax Base'!L11) -> 6.9512945 | L13: =LOG('Dataset Tax & Tax Base'!N11) -> 6.0821938 | M13: =LOG('Dataset Tax & Tax Base'!O11) -> 6.2675955 | N13: =LOG('Dataset Tax & Tax Base'!P11) -> 6.0045806
B14: 2007-08 | C14: =LOG('Dataset Tax & Tax Base'!C12) -> 5.5886761 | D14: =LOG('Dataset Tax & Tax Base'!D12) -> 5.2923314 | E14: =LOG('Dataset Tax & Tax Base'!E12) -> 5.2586277 | F14: =LOG('Dataset Tax & Tax Base'!G12) -> 4.9644341 | G14: =LOG('Dataset Tax & Tax Base'!H12) -> 5.1780066 | H14: =LOG('Dataset Tax & Tax Base'!I12) -> 6.0034997 | J14: =LOG('Dataset Tax & Tax Base'!K12) -> 7.1019922 | K14: =LOG('Dataset Tax & Tax Base'!L12) -> 7.0031706 | L14: =LOG('Dataset Tax & Tax Base'!N12) -> 6.1660104 | M14: =LOG('Dataset Tax & Tax Base'!O12) -> 6.4000321 | N14: =LOG('Dataset Tax & Tax Base'!P12) -> 6.1084622
B15: 2008-09 | C15: =LOG('Dataset Tax & Tax Base'!C13) -> 5.6469409 | D15: =LOG('Dataset Tax & Tax Base'!D13) -> 5.309023 | E15: =LOG('Dataset Tax & Tax Base'!E13) -> 5.3945025 | F15: =LOG('Dataset Tax & Tax Base'!G13) -> 5.0698715 | G15: =LOG('Dataset Tax & Tax Base'!H13) -> 5.1714427 | H15: =LOG('Dataset Tax & Tax Base'!I13) -> 6.0648884 | J15: =LOG('Dataset Tax & Tax Base'!K13) -> 7.1674856 | K15: =LOG('Dataset Tax & Tax Base'!L13) -> 7.060765 | L15: =LOG('Dataset Tax & Tax Base'!N13) -> 6.1977931 | M15: =LOG('Dataset Tax & Tax Base'!O13) -> 6.4351385 | N15: =LOG('Dataset Tax & Tax Base'!P13) -> 6.1263357
B16: 2009-10 | C16: =LOG('Dataset Tax & Tax Base'!C14) -> 5.7209668 | D16: =LOG('Dataset Tax & Tax Base'!D14) -> 5.3931293 | E16: =LOG('Dataset Tax & Tax Base'!E14) -> 5.4299169 | F16: =LOG('Dataset Tax & Tax Base'!G14) -> 5.0961593 | G16: =LOG('Dataset Tax & Tax Base'!H14) -> 5.2048596 | H16: =LOG('Dataset Tax & Tax Base'!I14) -> 6.1229959 | J16: =LOG('Dataset Tax & Tax Base'!K14) -> 7.2176695 | K16: =LOG('Dataset Tax & Tax Base'!L14) -> 7.1059119 | L16: =LOG('Dataset Tax & Tax Base'!N14) -> 6.2577374 | M16: =LOG('Dataset Tax & Tax Base'!O14) -> 6.4640385 | N16: =LOG('Dataset Tax & Tax Base'!P14) -> 6.1250611
B17: 2010-11 | C17: =LOG('Dataset Tax & Tax Base'!C15) -> 5.7799217 | D17: =LOG('Dataset Tax & Tax Base'!D15) -> 5.4894635 | E17: =LOG('Dataset Tax & Tax Base'!E15) -> 5.5114943 | F17: =LOG('Dataset Tax & Tax Base'!G15) -> 5.1378381 | G17: =LOG('Dataset Tax & Tax Base'!H15) -> 5.2668265 | H17: =LOG('Dataset Tax & Tax Base'!I15) -> 6.1925714 | J17: =LOG('Dataset Tax & Tax Base'!K15) -> 7.2951498 | K17: =LOG('Dataset Tax & Tax Base'!L15) -> 7.1769928 | L17: =LOG('Dataset Tax & Tax Base'!N15) -> 6.3436309 | M17: =LOG('Dataset Tax & Tax Base'!O15) -> 6.538484 | N17: =LOG('Dataset Tax & Tax Base'!P15) -> 6.1822231
B18: 2011-12 | C18: =LOG('Dataset Tax & Tax Base'!C16) -> 5.8683058 | D18: =LOG('Dataset Tax & Tax Base'!D16) -> 5.6338713 | E18: =LOG('Dataset Tax & Tax Base'!E16) -> 5.5734518 | F18: =LOG('Dataset Tax & Tax Base'!G16) -> 5.0880084 | G18: =LOG('Dataset Tax & Tax Base'!H16) -> 5.3362716 | H18: =LOG('Dataset Tax & Tax Base'!I16) -> 6.2747795 | J18: =LOG('Dataset Tax & Tax Base'!K16) -> 7.3491733 | K18: =LOG('Dataset Tax & Tax Base'!L16) -> 7.2334804 | L18: =LOG('Dataset Tax & Tax Base'!N16) -> 6.4075948 | M18: =LOG('Dataset Tax & Tax Base'!O16) -> 6.6030461 | N18: =LOG('Dataset Tax & Tax Base'!P16) -> 6.2041705
... B32: 2025-26* | C32: =LOG('Dataset Tax & Tax Base'!C30) -> 6.838975 | D32: =LOG('Dataset Tax & Tax Base'!D30) -> 6.4622976 | E32: =LOG('Dataset Tax & Tax Base'!E30) -> 6.2680324 | F32: =LOG('Dataset Tax & Tax Base'!G30) -> 5.948413 | G32: =LOG('Dataset Tax & Tax Base'!H30) -> 6.2008505 | H32: =LOG('Dataset Tax & Tax Base'!I30) -> 7.1501729 | J32: =LOG('Dataset Tax & Tax Base'!K30) -> 8.1010421 | K32: =LOG('Dataset Tax & Tax Base'!L30) -> 7.9875329 | L32: =LOG('Dataset Tax & Tax Base'!N30) -> 7.0396864 | M32: =LOG('Dataset Tax & Tax Base'!O30) -> 7.2671013 | N32: =LOG('Dataset Tax & Tax Base'!P30) -> 6.9391992
C34: DT | D34: STM | E34: STD | F34: FED | G34: CD | H34: TOTAL
C35: =+SLOPE(C7:C32,K7:K32) -> 1.2398209 | D35: =+SLOPE(D7:D32,M7:M32) -> 1.0085246 | E35: =+SLOPE(E7:E32,L7:L32) -> 1.0253544 | F35: =+SLOPE(F7:F32,L7:L32) -> 0.87999719 | G35: =+SLOPE(G7:G32,N7:N32) -> 1.0364462 | H35: =+SLOPE(H7:H32,J7:J32) -> 1.1233592
C39: Base Growth Assumptions (%) | E39: Buoyancy Estimates (%) | H39: Autonomous Growth (%)
C40: GDP (Nominal) | D40: 10.8 | E40: DT | G40: =C35 -> 1.2398209 | H40: DT (GDPN * DTBuoy) | J40: =D40*G40 -> 13.390065
C41: LSM(Nominal) | D41: 4.9 | E41: ST D | G41: =E35 -> 1.0253544 | H41: ST(D) (LSMN * STDBuoy) | J41: =D41*G41 -> 5.0242363
C42: Total Imports | D42: 13.4 | E42: STM | G42: =D35 -> 1.0085246 | H42: STM (Imports * STMBuoy) | J42: =D42*G42 -> 13.514229
C43: Inflation | D43: 6.1 | E43: Customs | G43: =G35 -> 1.0364462 | H43: CD (Imports * CDBuoy) | J43: =D42*G43 -> 13.88838
C44: GDP (Real) | D44: 4 | E44: FED | G44: =F35 -> 0.87999719 | H44: FED (LSMN * FEDBuoy) | J44: =D41*G44 -> 4.3119863

Sheet Econometric model Vs Buoyancy
B2: Tax Types | C2: Expected Base Figures 2025-26 | D2: Projections 2026-27 w/o measures | E2: Other models Projection | F2: 80% interval | G2: 95% interval | H2: Models used
B3: DT | C3: 6902 | D3: 7826.1823 | E3: 7329 | F3: [6,604 - 8050] | G3: [6,239 - 8608] | H3: ARDL
B4: ST(D) | C4: 1853.67 | D4: 1946.8028 | E4: - | F4: - | G4: - | H4: -
B5: ST(M) | C5: 2899.33 | D5: 3291.1521 | E5: - | F5: - | G5: - | H5: -
B6: ST(Total) | C6: 4753 | D6: 5237.9549 | E6: 4730 | F6: [4,194 - 5,188] | G6: [3,295 - 6,055] | H6: Elastic net (ML model)
B7: CD | C7: 1588 | D7: 1808.5475 | E7: 1592 | F7: [1,414 - 1,767] | G7: [1,364 - 1,943] | H7: ARDL
B8: FED | C8: 888 | D8: 926.29044 | E8: 1399 | F8: [1,162 - 1,640] | G8: [1,068 - 1,831] | H8: ARDL
B9: Total | C9: 14131 | D9: 15798.975 | E9: 15051 | F9: [13,373, 16,645] | G9: [11,967, 18,438]

Sheet Sensitivity Analysis
A1: Sensitivity Analysis
B5: Base for 2025-26 | C5: Direct Taxes | D5: Sales -imports | E5: Sales - Domestic | F5: Total Sales Tax | G5: FEDERAL | H5: CUSTOMS | I5: TOTAL
C6: 6755478 | D6: 2640955 | E6: 1688480 | F6: 4329435 | G6: 839352 | H6: 1309059 | I6: 13233324
I8: Rs Billion
C9: DT | D9: ST(D) | E9: ST(M) | F9: ST(Total) | G9: CD | H9: FED | I9: Total
B10: Expected Base Figures 2025-26 | C10: ='Sensitivity Analysis'!C6/1000 -> 6755.478 | D10: ='Sensitivity Analysis'!E6/1000 -> 1688.48 | E10: ='Sensitivity Analysis'!D6/1000 -> 2640.955 | F10: =SUM(D10:E10) -> 4329.435 | G10: =H6/1000 -> 1309.059 | H10: =G6/1000 -> 839.352 | I10: =I6/1000 -> 13233.324
B11: Addition with Autonomous growth | C11: =C10*('Tax Buoyancy Estimates'!J40/100) -> 904.56292 | D11: =D10*('Tax Buoyancy Estimates'!J41/100) -> 84.833226 | E11: =E10*('Tax Buoyancy Estimates'!J42/100) -> 356.90472 | F11: =SUM(D11:E11) -> 441.73794 | G11: =G10*('Tax Buoyancy Estimates'!J43/100) -> 181.80708 | H11: =H10*('Tax Buoyancy Estimates'!J44/100) -> 36.192743 | I11: =SUM(C11,F11,G11,H11) -> 1564.3007
B12: Projections 2026-27 w/o measures | C12: =C10+C11 -> 7660.0409 | D12: =D10+D11 -> 1773.3132 | E12: =E10+E11 -> 2997.8597 | F12: =F10+F11 -> 4771.1729 | G12: =G10+G11 -> 1490.8661 | H12: =H10+H11 -> 875.54474 | I12: =I10+I11 -> 14797.625
B13: Growth (%) | C13: ='Tax Buoyancy Estimates'!J40 -> 13.390065 | D13: ='Tax Buoyancy Estimates'!J41 -> 5.0242363 | E13: ='Tax Buoyancy Estimates'!J42 -> 13.514229 | F13: =SUM(D13:E13) -> 18.538466 | G13: ='Tax Buoyancy Estimates'!J43 -> 13.88838 | H13: ='Tax Buoyancy Estimates'!J44 -> 4.3119863 | I13: =SUM(C13,F13,G13,H13) -> 50.128897
B18: Growth Rate Variation (Robustness check)
B19: 10% Reduction in Growth Rate | C19: DT | D19: ST(D) | E19: ST(M) | F19: ST(Total) | G19: CD | H19: FED | I19: Total
B20: Expected Collection FY 2025-26 | C20: =C10 -> 6755.478 | D20: =D10 -> 1688.48 | E20: =E10 -> 2640.955 | F20: =F10 -> 4329.435 | G20: =G10 -> 1309.059 | H20: =H10 -> 839.352 | I20: =I10 -> 13233.324
B21: Tax wise 10% Reduced Autonomous Growth rates | C21: =C13*0.9 -> 12.051059 | D21: =D13*0.9 -> 4.5218127 | E21: =E13*0.9 -> 12.162806 | F21: =F13*0.9 -> 16.684619 | G21: =G13*0.9 -> 12.499542 | H21: =H13*0.9 -> 3.8807876 | I21: =I13*0.9 -> 45.116007
B22: FBR Forecast without Measures FY 2026-27 | C22: =C20*(1+(C21/100)) -> 7569.5846 | F22: =F20*(1+(F21/100)) -> 5051.7847 | G22: =G20*(1+(G21/100)) -> 1472.6854 | H22: =H20*(1+(H21/100)) -> 871.92547 | I22: =I20*(1+(I21/100)) -> 19203.671
B25: 10% Increase in Growth Rate | C25: DT | D25: ST(D) | E25: ST(M) | F25: ST(Total) | G25: CD | H25: FED | I25: Total
B26: Expected Collection FY 2025-26 | C26: =C10 -> 6755.478 | D26: =D10 -> 1688.48 | E26: =E10 -> 2640.955 | F26: =F10 -> 4329.435 | G26: =G10 -> 1309.059 | H26: =H10 -> 839.352 | I26: =I10 -> 13233.324
B27: Tax wise 10% Reduced Autonomous Growth rates | C27: =C13*1.1 -> 14.729072 | D27: =D13*1.1 -> 5.52666 | E27: =E13*1.1 -> 14.865652 | F27: =F13*1.1 -> 20.392312 | G27: =G13*1.1 -> 15.277218 | H27: =H13*1.1 -> 4.7431849 | I27: =I13*1.1 -> 55.141787
B28: FBR Forecast without Measures FY 2026-27 | C28: =C26*(1+(C27/100)) -> 7750.4972 | F28: =F26*(1+(F27/100)) -> 5212.3069 | G28: =G26*(1+(G27/100)) -> 1509.0468 | H28: =H26*(1+(H27/100)) -> 879.16402 | I28: =I26*(1+(I27/100)) -> 20530.415

Sheet Macro Projection MOF
D2: Indicators | E2: 2023-24 | F2: 2024-25 | G2: 2025-26 | H2: 2026-27 | I2: 2027-28 | J2: 2028-29
E3: Final | F3: Baseline | G3: Projected
D5: Economic Growth
D6: GDP at Basic Prices (Const Price) (%) | E6: 2.6 | F6: 3.1 | G6: 4 | H6: 5.1 | I6: 5.6 | J6: 5.8
D7: LSM (%) | E7: 0.9 | F7: -0.7 | G7: 4.9 | H7: 6.8 | I7: 7.1 | J7: 8
D8: Inflation (Average) | E8: 23.4 | F8: 4.5 | G8: 6.1 | H8: 6.5 | I8: 6.5 | J8: 6.7
D9: GDP at Market Prices (Rs Billion) | E9: 105379 | F9: 113935 | G9: 126195 | H9: 141663 | I9: 159245 | J9: 178969
D10: Growth in Nominal GDP (%) | E10: 25.9 | F10: 8.1 | G10: 10.8 | H10: 12.3 | I10: 12.4 | J10: 12.4
D11: External Sector $ million
D12: Current Account $ million | E12: -2072 | F12: 1932 | G12: -2119 | H12: -1986 | I12: -3552 | J12: -4803
D13: CA as % of GDP | E13: -0.6 | F13: 0.5 | G13: -0.5 | H13: -0.4 | I13: -0.7 | J13: -0.8
D14: Exports (goods) $ million | E14: 30980 | F14: 32340 | G14: 34005 | H14: 37452 | I14: 41387 | J14: 45935
D15: Imports (goods) $ million | E15: 53157 | F15: 59111 | G15: 65298 | H15: 70647 | I15: 77626 | J15: 85547
D16: Exports (Services) $ million | E16: 7691 | F16: 8408 | G16: 8501 | H16: 9422 | I16: 10412 | J16: 11556
D17: Imports (Services) $ million | E17: 10801 | F17: 11053 | G17: 12438 | H17: 13457 | I17: 14786 | J17: 16295
D18: Workers Remittances $ million | E18: 30251 | F18: 38299 | G18: 41491 | H18: 43854 | I18: 45914 | J18: 47905
D19: External Sector (Rs Billion)
D20: Exports (goods) | E20: 8702 | F20: 8967 | G20: 9632 | H20: 10738 | I20: 12098 | J20: 13592
D21: Imports (goods) | E21: 14932 | F21: 16307 | G21: 18497 | H21: 20254 | I21: 22690 | J21: 25313
D22: Exports (Services) | E22: 2160 | F22: 2345 | G22: 2408 | H22: 2701 | I22: 3043 | J22: 3419
D23: Imports (Services) | E23: 3034 | F23: 3077 | G23: 3523 | H23: 3858 | I23: 4322 | J23: 4822
